dongdong/BarkNotificator.py
dongdong/DesktopNotificator.py
dongdong/DingTalkNotificator.py
dongdong/SetConfigures.py
dongdong/TeamsNotificator.py
dongdong/WechatNotificator.py
dongdong/__init__.py
dongdong/configure.py
dongdong-0.0.4.dist-info/LICENSE
dongdong-0.0.4.dist-info/METADATA
dongdong-0.0.4.dist-info/WHEEL
dongdong-0.0.4.dist-info/entry_points.txt
dongdong-0.0.4.dist-info/top_level.txt
dongdong-0.0.4.dist-info/RECORD
